{
  "_class": "group",
  "do_objectID": "C12DD6DE-2039-4D96-851C-AD7F1562EDE6",
  "exportOptions": {
    "_class": "exportOptions",
    "exportFormats": [
    ],
    "includedLayerIds": [
    ],
    "layerOptions": 0,
    "shouldTrim": false
  },
  "frame": {
    "_class": "rect",
    "constrainProportions": false,
    "height": 157,
    "width": 122,
    "x": 0,
    "y": 0
  },
  "hasClickThrough": false,
  "isFlippedHorizontal": false,
  "isFlippedVertical": false,
  "isLocked": false,
  "isVisible": true,
  "layerListExpandedType": 2,
  "layers": [
    {
      "class": "shapeGroup",
      "id": "EF55D57E-E53C-41EB-97AF-05CACCE49AC0"
    },
    {
      "class": "group",
      "id": "BB5BC2B5-44A5-46D6-AD09-62BFD5FD066E"
    }
  ],
  "name": "Group 10",
  "nameIsFixed": false,
  "resizingConstraint": 63,
  "resizingType": 0,
  "rotation": 0,
  "shouldBreakMaskChain": false,
  "style": {
    "_class": "style",
    "endDecorationType": 0,
    "miterLimit": 10,
    "shadows": [
      {
        "_class": "shadow",
        "blurRadius": 55,
        "color": {
          "_class": "color",
          "alpha": 0.7362432065217391,
          "blue": 0.8291951393594548,
          "green": 0.8291951393594548,
          "red": 0.9871120323129252
        },
        "contextSettings": {
          "_class": "graphicsContextSettings",
          "blendMode": 2,
          "opacity": 1
        },
        "isEnabled": true,
        "offsetX": 5,
        "offsetY": 5,
        "spread": 0
      }
    ],
    "startDecorationType": 0
  },
  "userInfo": {
    "com.animaapp.stc-sketch-plugin": {
      "kModelPropertiesKey": {
      }
    }
  }
}